ad3/__init__.py
ad3/base.cpp
ad3/base.pxd
ad3/base.pyd
ad3/base.pyx
ad3/extensions.cpp
ad3/extensions.pyd
ad3/extensions.pyx
ad3/factor_graph.cpp
ad3/factor_graph.pyd
ad3/factor_graph.pyx
ad3/simple_constrained_inference.py
ad3/simple_inference.py
ad3/tests/__init__.py
ad3/tests/test_basic_factors.py
ad3/tests/test_budget_factors.py
ad3/tests/test_factor_graph.py
ad3/tests/test_pystruct.py
ad3/tests/test_sequence.py
ad3/tests/test_simple_constrained_inference.py
ad3/tests/test_simple_inference.py
ad3/tests/test_solve.py
ad3/tests/test_tree_factor.py
ad3/tests/test_variables.py
ad3-2.2.1.dist-info/METADATA
ad3-2.2.1.dist-info/RECORD
ad3-2.2.1.dist-info/WHEEL
ad3-2.2.1.dist-info/top_level.txt
