Metadata-Version: 2.1
Name: ad3
Version: 2.2.1
Summary: Alternating Directions Dual Decomposition
Home-page: http://www.ark.cs.cmu.edu/AD3
Author: Andre Martins
Author-email: afm@cs.cmu.edu
License: UNKNOWN
Platform: UNKNOWN
